metapkg/__init__.py
metapkg/cli.py
metapkg/import_scanner.py
metapkg/req_writer.py
metapkg/toml_manager.py
metapkg/utils.py
metapkg-0.1.3.dist-info/licenses/LICENSE
metapkg-0.1.3.dist-info/METADATA
metapkg-0.1.3.dist-info/WHEEL
metapkg-0.1.3.dist-info/entry_points.txt
metapkg-0.1.3.dist-info/top_level.txt
metapkg-0.1.3.dist-info/RECORD
