Metadata-Version: 2.4
Name: metapkg
Version: 0.1.3
Summary: CLI tool to manage pyproject.toml and generate requirements.txt
Author: Harsh Dadiya
License: MIT
Project-URL: Homepage, https://github.com/Dadiya-Harsh/metapkg
Project-URL: Source, https://github.com/Dadiya-Harsh/metapkg
Classifier: Development Status :: 3 - Alpha
Classifier: Intended Audience :: Developers
Classifier: License :: OSI Approved :: MIT License
Classifier: Programming Language :: Python :: 3
Classifier: Programming Language :: Python :: 3.12
Classifier: Topic :: Software Development :: Build Tools
Requires-Python: >=3.10
License-File: LICENSE
Requires-Dist: build>=1.2.2.post1
Requires-Dist: click>=8.1.8
Requires-Dist: markdown-it-py>=3.0.0
Requires-Dist: mdurl>=0.1.2
Requires-Dist: pygments>=2.19.1
Requires-Dist: rich>=14.0.0
Requires-Dist: shellingham>=1.5.4
Requires-Dist: tomli>=2.2.1
Requires-Dist: tomli-w>=1.2.0
Requires-Dist: twine>=6.1.0
Requires-Dist: typer>=0.15.3
Requires-Dist: typing-extensions>=4.13.2
Dynamic: license-file
